guillotina_swagger/__init__.py
guillotina_swagger/content.py
guillotina_swagger/index.html
guillotina_swagger/services.py
guillotina_swagger/utils.py
guillotina_swagger/static/integration.js
guillotina_swagger/static/o2c.html
guillotina_swagger/static/styles.css
guillotina_swagger/static/swagger-ui.js
guillotina_swagger/static/swagger-ui.min.js
guillotina_swagger/static/css/print.css
guillotina_swagger/static/css/reset.css
guillotina_swagger/static/css/screen.css
guillotina_swagger/static/css/style.css
guillotina_swagger/static/css/typography.css
guillotina_swagger/static/fonts/DroidSans-Bold.ttf
guillotina_swagger/static/fonts/DroidSans.ttf
guillotina_swagger/static/images/collapse.gif
guillotina_swagger/static/images/expand.gif
guillotina_swagger/static/images/explorer_icons.png
guillotina_swagger/static/images/favicon-16x16.png
guillotina_swagger/static/images/favicon-32x32.png
guillotina_swagger/static/images/favicon.ico
guillotina_swagger/static/images/logo_small.png
guillotina_swagger/static/images/pet_store_api.png
guillotina_swagger/static/images/throbber.gif
guillotina_swagger/static/images/wordnik_api.png
guillotina_swagger/static/lang/ca.js
guillotina_swagger/static/lang/el.js
guillotina_swagger/static/lang/en.js
guillotina_swagger/static/lang/es.js
guillotina_swagger/static/lang/fr.js
guillotina_swagger/static/lang/geo.js
guillotina_swagger/static/lang/it.js
guillotina_swagger/static/lang/ja.js
guillotina_swagger/static/lang/ko-kr.js
guillotina_swagger/static/lang/pl.js
guillotina_swagger/static/lang/pt.js
guillotina_swagger/static/lang/ru.js
guillotina_swagger/static/lang/tr.js
guillotina_swagger/static/lang/translator.js
guillotina_swagger/static/lang/zh-cn.js
guillotina_swagger/static/lib/backbone-min.js
guillotina_swagger/static/lib/es5-shim.js
guillotina_swagger/static/lib/handlebars-4.0.5.js
guillotina_swagger/static/lib/highlight.9.1.0.pack.js
guillotina_swagger-1.0.13.dist-info/METADATA
guillotina_swagger-1.0.13.dist-info/RECORD
guillotina_swagger-1.0.13.dist-info/WHEEL
guillotina_swagger-1.0.13.dist-info/top_level.txt
