Metadata-Version: 2.1
Name: guillotina-swagger
Version: 1.0.13
Summary: Swagger integration for viewing REST on your guillotina install
Home-page: https://github.com/guillotinaweb/guillotina_swagger
Author: Nathan Van Gheem
Author-email: vangheem@gmail.com
License: BSD
Keywords: guillotina,REST,swagger
Platform: UNKNOWN
Classifier: License :: OSI Approved :: BSD License
Classifier: Intended Audience :: Developers
Classifier: Topic :: Internet :: WWW/HTTP
Classifier: Programming Language :: Python :: 3.6
Classifier: Topic :: Software Development :: Libraries :: Python Modules
Requires-Dist: guillotina
Requires-Dist: jinja2
